PRPG.v
module PRPG (Qout,clk,set);
input clk;
input set;
output [2:0]Qout;
reg [2:0]Qout;

always@(posedge clk)
begin
    if(set)
    begin
        Qout <= 3'b110;
    end
    else
    begin
        Qout[0] <= Qout[2] ^ Qout[0];
        Qout[1] <= Qout[0];
        Qout[2] <= Qout[1];
    end
end
endmodule

TestBench.v
`timescale 1ns/1ps

module TestBench();

reg set;
reg clk;
wire [2:0]Qout;

parameter PERIOD = 20;
parameter real DUTY_CYCLE = 0.5;
parameter OFFSET = 0;

initial
begin
    #OFFSET;
    forever
    begin
        clk = 1'b1;
        #(PERIOD-(PERIOD*DUTY_CYCLE)) clk = 1'b0;
        #(PERIOD*DUTY_CYCLE);
    end
end
initial
begin
    set = 1;
    #10  set = 0;
    #300 $finish;
end
initial
begin
    $dumpfile("PRPG.vcd");
    $dumpvars(0,prpg_tb);
end
PRPG prpg_tb(
         .Qout(Qout),
         .clk(clk),
         .set(set)
     );

endmodule

PRPG.vcd
$date
	Wed May 18 11:47:49 2022
$end
$version
	Icarus Verilog
$end
$timescale
	1ps
$end
$scope module TestBench $end
$scope module prpg_tb $end
$var wire 1 ! clk $end
$var wire 1 " set $end
$var reg 3 # Qout [2:0] $end
$upscope $end
$upscope $end
$enddefinitions $end
#0
$dumpvars
b110 #
1"
1!
$end
#10000
0!
0"
#20000
b101 #
1!
#30000
0!
#40000
b10 #
1!
#50000
0!
#60000
b100 #
1!
#70000
0!
#80000
b1 #
1!
#90000
0!
#100000
b11 #
1!
#110000
0!
#120000
b111 #
1!
#130000
0!
#140000
b110 #
1!
#150000
0!
#160000
b101 #
1!
#170000
0!
#180000
b10 #
1!
#190000
0!
#200000
b100 #
1!
#210000
0!
#220000
b1 #
1!
#230000
0!
#240000
b11 #
1!
#250000
0!
#260000
b111 #
1!
#270000
0!
#280000
b110 #
1!
#290000
0!
#300000
b101 #
1!
